llm_society/__init__.py
llm_society/__main__.py
llm_society/config.py
llm_society/orchestrator.py
llm_society/prompt_generator.py
llm_society/prompts.py
llm_society/schemas.py
pysociety-0.2.4.dist-info/METADATA
pysociety-0.2.4.dist-info/WHEEL
pysociety-0.2.4.dist-info/entry_points.txt
pysociety-0.2.4.dist-info/RECORD
