Metadata-Version: 2.4
Name: pysociety
Version: 0.2.4
Summary: Multi-agent society simulation with playful personalities
Requires-Python: >=3.12
Requires-Dist: deepagents>=0.1.0
Requires-Dist: instructor>=1.0.0
Requires-Dist: pydantic>=2.12.5
Requires-Dist: python-dotenv>=1.2.1
